argskwargsmodifier/README.MD
argskwargsmodifier/__init__.py
argskwargsmodifier/requirements.txt
argskwargsmodifier/thirdparty.json
argskwargsmodifier-0.10.dist-info/LICENSE.rst
argskwargsmodifier-0.10.dist-info/METADATA
argskwargsmodifier-0.10.dist-info/WHEEL
argskwargsmodifier-0.10.dist-info/top_level.txt
argskwargsmodifier-0.10.dist-info/RECORD
