Metadata-Version: 2.1
Name: argskwargsmodifier
Version: 0.10
Summary: A decorator that modifies the arguments and keyword arguments of a function before calling it.
Home-page: https://github.com/hansalemaos/argskwargsmodifier
Author: Johannes Fischer
Author-email: aulasparticularesdealemaosp@gmail.com
License: MIT
Keywords: decorator,args,kwargs
Classifier: Development Status :: 4 - Beta
Classifier: Programming Language :: Python :: 3 :: Only
Classifier: Programming Language :: Python :: 3.10
Classifier: Topic :: Software Development :: Libraries :: Python Modules
Classifier: Topic :: Utilities
License-File: LICENSE.rst
